gemapi/__init__.py
gemapi/applications.py
gemapi/certificates.py
gemapi-0.1.0.dist-info/LICENSE
gemapi-0.1.0.dist-info/WHEEL
gemapi-0.1.0.dist-info/METADATA
gemapi-0.1.0.dist-info/RECORD
