Metadata-Version: 2.1
Name: gemapi
Version: 0.1.0
Summary: Gemapi is a lightweight Gemini framework.
Home-page: https://git.sr.ht/~tsileo/gemapi
License: ISC
Author: Thomas Sileo
Author-email: t@a4.io
Requires-Python: >=3.10,<4.0
Classifier: License :: OSI Approved
Classifier: Programming Language :: Python :: 3
Classifier: Programming Language :: Python :: 3.10
Requires-Dist: loguru (>=0.6.0,<0.7.0)
Requires-Dist: pyOpenSSL (>=22.0.0,<23.0.0)
Project-URL: Bug Tracker, https://todo.sr.ht/~tsileo/gemapi
Project-URL: Repository, https://git.sr.ht/~tsileo/gemapi
